setup.py
pili/__init__.py
pili/api.py
pili/auth.py
pili/client.py
pili/conf.py
pili/errors.py
pili/hub.py
pili/stream.py
pili/urls.py
pili/utils.py
pili2.egg-info/PKG-INFO
pili2.egg-info/SOURCES.txt
pili2.egg-info/dependency_links.txt
pili2.egg-info/top_level.txt