Metadata-Version: 1.0
Name: pili2
Version: 2.0.0
Summary: Pili Streaming Cloud Server-Side Library For Python
Home-page: UNKNOWN
Author: Pili Engineering
Author-email: pili@qiniu.com
License: MIT License
Keywords: pili,streaming,hls,rtmp
Platform: any
